vodacash/__init__.py
vodacompay-3.1.4.dist-info/LICENSE
vodacompay-3.1.4.dist-info/METADATA
vodacompay-3.1.4.dist-info/WHEEL
vodacompay-3.1.4.dist-info/top_level.txt
vodacompay-3.1.4.dist-info/RECORD
