Metadata-Version: 2.1
Name: vodacompay
Version: 3.1.4
Summary: A library to interface with vodacom's Payment System using an intermediary server.
Home-page: https://github.com/TralahM/vodacompay
Author: Tralah M Brian
Author-email: briantralah@gmail.com
Classifier: Programming Language :: Python
Classifier: License :: OSI Approved :: MIT License
Classifier: Operating System :: OS Independent
License-File: LICENSE
Requires-Dist: certifi
Requires-Dist: chardet
Requires-Dist: future
Requires-Dist: idna
Requires-Dist: requests
Requires-Dist: six
Requires-Dist: urllib3
Requires-Dist: pytest
Requires-Dist: lxml
